money/__init__.py
money/currency.py
money/exceptions.py
money/exchange.py
money/money.py
money/django/__init__.py
money/django/fields.py
money/django/forms.py
money/django/widgets.py
money_lib-3.1.0.dist-info/LICENSE
money_lib-3.1.0.dist-info/METADATA
money_lib-3.1.0.dist-info/WHEEL
money_lib-3.1.0.dist-info/top_level.txt
money_lib-3.1.0.dist-info/RECORD
