Metadata-Version: 2.1
Name: money-lib
Version: 3.1.0
Summary: Python 3 money lib with decimal precision and currency exchange support.
Author-email: Rui Pereira <me@ruipereira.dev>
License: MIT
Project-URL: Homepage, https://github.com/r4g3baby/money-lib
Project-URL: Bug Tracker, https://github.com/r4g3baby/money-lib/issues
Classifier: Development Status :: 5 - Production/Stable
Classifier: License :: OSI Approved :: MIT License
Classifier: Operating System :: OS Independent
Classifier: Intended Audience :: Developers
Classifier: Programming Language :: Python
Classifier: Programming Language :: Python :: 3
Classifier: Programming Language :: Python :: 3.7
Classifier: Programming Language :: Python :: 3.8
Classifier: Programming Language :: Python :: 3.9
Classifier: Programming Language :: Python :: 3.10
Classifier: Programming Language :: Python :: 3.11
Requires-Python: >=3.7
License-File: LICENSE
Requires-Dist: Babel (>=2.5.0)
Provides-Extra: django
Requires-Dist: Django (>=3.2) ; extra == 'django'
